chumba/__init__.py
chumba/statistic.py
chumba/utils.py
chumba/word.py
chumba/data/encodings.txt
chumba/data/ojegov.txt
chumba/data/words_en.txt
chumba/data/words_ru.txt
chumba-0.0.4.dist-info/LICENSE
chumba-0.0.4.dist-info/METADATA
chumba-0.0.4.dist-info/WHEEL
chumba-0.0.4.dist-info/top_level.txt
chumba-0.0.4.dist-info/RECORD
