Metadata-Version: 2.1
Name: chumba
Version: 0.0.4
Summary: Useful set of tools to work with texts
Author-email: kotolex <lexman2@yandex.ru>
Project-URL: Homepage, https://github.com/kotolex/chumba
Project-URL: Bug Tracker, https://github.com/kotolex/chumba/issues
Classifier: Programming Language :: Python :: 3
Classifier: License :: OSI Approved :: MIT License
Classifier: Operating System :: OS Independent
Requires-Python: >=3.7
License-File: LICENSE
